jentic/apitools/openapi/validator/backends/redocly/__init__.py
jentic/apitools/openapi/validator/backends/redocly/py.typed
jentic/apitools/openapi/validator/backends/redocly/rulesets/redocly.yaml
jentic_openapi_validator_redocly-1.0.0a34.dist-info/licenses/LICENSE
jentic_openapi_validator_redocly-1.0.0a34.dist-info/licenses/NOTICE
jentic_openapi_validator_redocly-1.0.0a34.dist-info/WHEEL
jentic_openapi_validator_redocly-1.0.0a34.dist-info/entry_points.txt
jentic_openapi_validator_redocly-1.0.0a34.dist-info/METADATA
jentic_openapi_validator_redocly-1.0.0a34.dist-info/RECORD
